vunit_py/__init__.py
vunit_py/event_clock.py
vunit_py/module_parser.py
vunit_py/port.py
vunit_py/signal_helper.py
vunit_py/test.py
vunit_py/value.py
vunit_py-0.0.2.dist-info/licenses/LICENSE
vunit_py-0.0.2.dist-info/METADATA
vunit_py-0.0.2.dist-info/WHEEL
vunit_py-0.0.2.dist-info/top_level.txt
vunit_py-0.0.2.dist-info/RECORD
