Metadata-Version: 2.4
Name: vunit-py
Version: 0.0.2
Summary: Generating testbench written in python for VUnit
Author-email: Weiyi Wu <w1w2y3@gmail.com>
License-Expression: GPL-3.0-or-later
Project-URL: Homepage, https://github.com/wwy9/vunit-py
Classifier: Development Status :: 3 - Alpha
Classifier: Intended Audience :: Developers
Classifier: Natural Language :: Chinese (Simplified)
Classifier: Operating System :: OS Independent
Classifier: Programming Language :: Python :: 3.6
Classifier: Programming Language :: Python :: 3.7
Classifier: Programming Language :: Python :: 3.8
Classifier: Topic :: Software Development :: Testing
Classifier: Topic :: Scientific/Engineering :: Electronic Design Automation (EDA)
Classifier: Typing :: Typed
Requires-Python: >=3.6
License-File: LICENSE
Requires-Dist: vunit_hdl>=4.7.0
Dynamic: license-file
